{
  "biography": "I was here.",
  "taskLists": {
    "id": 1,
    "subTaskLists": [
      {
        "id": 4,
        "title": "TaskList 2",
        "description": "Second tasklist",
        "comment": "When the default tasklist just isn\u0027t good enough.",
        "subTaskLists": [
          {
            "id": 5,
            "title": "Sub-TaskList",
            "description": "Sub-tasklist.",
            "comment": "Some comment.",
            "subTaskLists": [
              {
                "id": 6,
                "title": "Sub-Sub-TaskList",
                "description": "Sub-sub-tasklist.",
                "comment": "Yeah, I went there.",
                "sections": [
                  {
                    "id": 7,
                    "tasks": [],
                    "defaultSection": true,
                    "parentTaskListID": -1
                  },
                  {
                    "id": 8,
                    "title": "Section 2",
                    "description": "Additional section.",
                    "tasks": [],
                    "defaultSection": false,
                    "parentTaskListID": 6
                  }
                ],
                "isListArchived": false,
                "parentTaskListID": 5
              }
            ],
            "sections": [
              {
                "id": 5,
                "tasks": [],
                "defaultSection": true,
                "parentTaskListID": -1
              }
            ],
            "isListArchived": false,
            "parentTaskListID": 4
          }
        ],
        "sections": [
          {
            "id": 4,
            "tasks": [
              {
                "id": 2,
                "title": "Task 3",
                "description": "task 3 description",
                "parentTaskID": -1,
                "parentSectionID": 4
              },
              {
                "id": 3,
                "title": "Task 4",
                "description": "task 4 description",
                "parentTaskID": -1,
                "parentSectionID": 4
              }
            ],
            "defaultSection": true,
            "parentTaskListID": -1
          },
          {
            "id": 6,
            "title": "Section 1",
            "description": "Additional section.",
            "tasks": [
              {
                "id": 4,
                "title": "Task 5",
                "description": "task 5 description",
                "dueDate": {
                  "year": 2021,
                  "month": 3,
                  "dayOfMonth": 26,
                  "hourOfDay": 16,
                  "minute": 58,
                  "second": 23
                },
                "subtasks": [
                  {
                    "id": 6,
                    "title": "Task 7",
                    "description": "task 7 description",
                    "parentTaskID": 4,
                    "parentSectionID": -2
                  }
                ],
                "parentTaskID": -1,
                "parentSectionID": 6
              },
              {
                "id": 5,
                "title": "Task 6",
                "description": "task 6 description",
                "dueDate": {
                  "year": 2021,
                  "month": 3,
                  "dayOfMonth": 26,
                  "hourOfDay": 16,
                  "minute": 58,
                  "second": 23
                },
                "parentTaskID": -1,
                "parentSectionID": 6
              }
            ],
            "defaultSection": false,
            "parentTaskListID": 4
          }
        ],
        "isListArchived": false,
        "parentTaskListID": 1
      }
    ],
    "sections": [
      {
        "id": 1,
        "tasks": [
          {
            "id": 0,
            "title": "Task 1",
            "description": "task 1 description",
            "parentTaskID": -1,
            "parentSectionID": 1
          },
          {
            "id": 1,
            "title": "Task 2",
            "description": "task 2 description",
            "parentTaskID": -1,
            "parentSectionID": 1
          },
          {
            "id": 7,
            "title": "Task 8",
            "description": "task 8 description",
            "parentTaskID": -1,
            "parentSectionID": 1
          }
        ],
        "defaultSection": true,
        "parentTaskListID": -1
      }
    ],
    "isListArchived": false,
    "parentTaskListID": -1
  },
  "id": 0,
  "email": "test@gmail.com",
  "password": "b109f3bbbc244eb82441917ed06d618b9008dd09b3befd1b5e07394c706a8bb980b1d7785e5976ec049b46df5f1326af5a2ea6d103fd07c95385ffab0cacbc86",
  "firstName": "Brandon",
  "lastName": "Watkins"
}